[
  {
    "class_name": "Headlight - -R-",
    "confidence": 0.7172631025314331,
    "bbox": [
      8.51806354522705,
      61.1423225402832,
      42.9250373840332,
      87.75910186767578
    ],
    "center_point": [
      25,
      74
    ],
    "segmented_image_path": "D:\\FINAL YEAR PROJECT (FYP)\\RCMS_Web\\public\\segments\\1750169318150\\Headlight - -R-_0_0.72.jpg",
    "mask_path": "D:\\FINAL YEAR PROJECT (FYP)\\RCMS_Web\\public\\segments\\1750169318150\\Headlight - -R-_0_mask.jpg",
    "mask_area": 430
  },
  {
    "class_name": "Headlight - -L-",
    "confidence": 0.45710110664367676,
    "bbox": [
      8.37180233001709,
      61.4953498840332,
      42.6307373046875,
      87.80628204345703
    ],
    "center_point": [
      25,
      74
    ],
    "segmented_image_path": "D:\\FINAL YEAR PROJECT (FYP)\\RCMS_Web\\public\\segments\\1750169318150\\Headlight - -L-_1_0.46.jpg",
    "mask_path": "D:\\FINAL YEAR PROJECT (FYP)\\RCMS_Web\\public\\segments\\1750169318150\\Headlight - -L-_1_mask.jpg",
    "mask_area": 430
  }
]